[
  {
    "title": "TEst notes",
    "type": "News",
    "category": "Interview",
    "subtype": "",
    "date": "2025-07-22T22:45",
    "location": "Studio",
    "priority": "Normal",
    "camOp": true,
    "shootType": "ENG",
    "notes": [
      {
        "text": "NOTE NOTE NOTE",
        "author": "Admin",
        "timestamp": "7/22/2025, 9:50:37 PM"
      }
    ],
    "camCount": 1,
    "onlyOneCamOp": true,
    "camAssignments": {
      "cam1": "",
      "cam2": "",
      "cam3": ""
    },
    "departureTime": "22:15",
    "filmingTime": "22:45",
    "assignedCamOps": [],
    "assignedDriver": "",
    "vehicle": "",
    "assignmentStatus": "Unassigned",
    "isReady": false,
    "status": "Pending",
    "assignedReporter": "Journalist: Naila D'acambra",
    "vehicleStatus": "",
    "createdBy": "Admin",
    "createdAt": "2025-07-22T17:50:37.064Z",
    "id": "1753206637372"
  },
  {
    "title": "Test 3",
    "type": "News",
    "category": "Interview",
    "subtype": "",
    "date": "2025-07-22T22:35",
    "location": "Town",
    "priority": "Normal",
    "camOp": true,
    "shootType": "ENG",
    "notes": [],
    "camCount": 1,
    "onlyOneCamOp": true,
    "camAssignments": {
      "cam1": "",
      "cam2": "",
      "cam3": ""
    },
    "departureTime": "22:05",
    "filmingTime": "22:35",
    "assignedCamOps": [],
    "assignedDriver": "",
    "vehicle": "",
    "assignmentStatus": "Unassigned",
    "isReady": false,
    "status": "Pending",
    "assignedReporter": "Journalist: George Francois",
    "vehicleStatus": "",
    "createdBy": "Admin",
    "createdAt": "2025-07-22T17:41:58.650Z",
    "id": "1753206118655"
  },
  {
    "title": "TEST Centre",
    "type": "News",
    "category": "",
    "subtype": "",
    "date": "2025-07-22T23:25",
    "location": "Providence",
    "priority": "Normal",
    "camOp": true,
    "shootType": "ENG",
    "notes": [],
    "camCount": 1,
    "onlyOneCamOp": true,
    "camAssignments": {
      "cam1": "",
      "cam2": "",
      "cam3": ""
    },
    "departureTime": "22:55",
    "filmingTime": "23:25",
    "assignedCamOps": [],
    "assignedDriver": "",
    "vehicle": "",
    "assignmentStatus": "Unassigned",
    "isReady": false,
    "status": "Pending",
    "assignedReporter": "Journalist: Kerine Savy",
    "vehicleStatus": "",
    "createdBy": "Admin",
    "createdAt": "2025-07-22T17:37:16.338Z",
    "id": "1753205836343"
  },
  {
    "title": "TEST Toast",
    "type": "News",
    "category": "",
    "subtype": "",
    "date": "2025-07-22T22:30",
    "location": "Studio",
    "priority": "Normal",
    "camOp": true,
    "shootType": "ENG",
    "notes": [],
    "camCount": 1,
    "onlyOneCamOp": true,
    "camAssignments": {
      "cam1": "",
      "cam2": "",
      "cam3": ""
    },
    "departureTime": "22:00",
    "filmingTime": "22:30",
    "assignedCamOps": [],
    "assignedDriver": "",
    "vehicle": "",
    "assignmentStatus": "Unassigned",
    "isReady": false,
    "status": "Pending",
    "assignedReporter": "Journalist: Joshua Sofola",
    "vehicleStatus": "",
    "createdBy": "Admin",
    "createdAt": "2025-07-22T17:34:41.536Z",
    "id": "1753205681541"
  },
  {
    "title": "TEST 4",
    "type": "News",
    "category": "",
    "subtype": "",
    "date": "2025-07-22T22:30",
    "location": "Providence",
    "priority": "Normal",
    "camOp": true,
    "shootType": "ENG",
    "notes": [],
    "camCount": 1,
    "onlyOneCamOp": true,
    "camAssignments": {
      "cam1": "",
      "cam2": "",
      "cam3": ""
    },
    "departureTime": "22:00",
    "filmingTime": "22:30",
    "assignedCamOps": [],
    "assignedDriver": "",
    "vehicle": "",
    "assignmentStatus": "Unassigned",
    "isReady": false,
    "status": "Pending",
    "assignedReporter": "Journalist: Melissa Hassan",
    "vehicleStatus": "",
    "createdBy": "Admin",
    "createdAt": "2025-07-22T17:34:07.829Z",
    "id": "1753205647834"
  },
  {
    "title": "TEST",
    "type": "News",
    "category": "",
    "subtype": "",
    "date": "2025-07-22T21:35",
    "location": "Providence",
    "priority": "Normal",
    "camOp": true,
    "shootType": "ENG",
    "notes": [],
    "camCount": 1,
    "onlyOneCamOp": true,
    "camAssignments": {
      "cam1": "",
      "cam2": "",
      "cam3": ""
    },
    "departureTime": "21:05",
    "filmingTime": "21:35",
    "assignedCamOps": [],
    "assignedDriver": "",
    "vehicle": "",
    "assignmentStatus": "Unassigned",
    "isReady": false,
    "status": "Pending",
    "assignedReporter": "Journalist: Ronny Solin",
    "vehicleStatus": "",
    "createdBy": "Admin",
    "createdAt": "2025-07-22T17:24:58.281Z",
    "id": "1753205098286",
    "deleted": true
  },
  {
    "title": "TEST",
    "type": "News",
    "category": "",
    "subtype": "",
    "date": "2025-07-22T22:55",
    "location": "",
    "priority": "Normal",
    "camOp": true,
    "shootType": "ENG",
    "notes": [],
    "camCount": 1,
    "onlyOneCamOp": true,
    "camAssignments": {
      "cam1": "",
      "cam2": "",
      "cam3": ""
    },
    "departureTime": "22:25",
    "filmingTime": "22:55",
    "assignedCamOps": [],
    "assignedDriver": "",
    "vehicle": "",
    "assignmentStatus": "Unassigned",
    "isReady": false,
    "status": "Pending",
    "assignedReporter": "Journalist: Naila D'acambra",
    "vehicleStatus": "",
    "createdBy": "Admin",
    "createdAt": "2025-07-22T17:22:45.193Z",
    "id": "1753204965198",
    "deleted": true
  },
  {
    "title": "TEST",
    "type": "News",
    "category": "",
    "subtype": "",
    "date": "2025-07-22T22:15",
    "location": "State House",
    "priority": "Normal",
    "camOp": true,
    "shootType": "ENG",
    "notes": [],
    "camCount": 1,
    "onlyOneCamOp": true,
    "camAssignments": {
      "cam1": "",
      "cam2": "",
      "cam3": ""
    },
    "departureTime": "21:45",
    "filmingTime": "22:15",
    "assignedCamOps": [],
    "assignedDriver": "",
    "vehicle": "",
    "assignmentStatus": "Unassigned",
    "isReady": false,
    "status": "Pending",
    "assignedReporter": "Journalist: Ronny Solin",
    "vehicleStatus": "",
    "createdBy": "Admin",
    "createdAt": "2025-07-22T17:22:13.724Z",
    "id": "1753204933729",
    "deleted": true
  },
  {
    "title": "TEST 1",
    "type": "News",
    "category": "",
    "subtype": "",
    "date": "2025-07-22T21:25",
    "location": "State House",
    "priority": "Normal",
    "camOp": true,
    "shootType": "ENG",
    "notes": [],
    "camCount": 1,
    "onlyOneCamOp": true,
    "camAssignments": {
      "cam1": "",
      "cam2": "",
      "cam3": ""
    },
    "departureTime": "21:25",
    "filmingTime": "21:25",
    "assignedCamOps": [],
    "assignedDriver": "",
    "vehicle": "",
    "assignmentStatus": "Unassigned",
    "isReady": false,
    "status": "Pending",
    "vehicleStatus": "",
    "assignedReporter": "Journalist Admin",
    "createdBy": "Admin",
    "createdAt": "2025-07-22T17:21:47.070Z",
    "id": "1753204907076",
    "deleted": true
  },
  {
    "title": "TEST 1",
    "type": "News",
    "category": "Interview",
    "subtype": "",
    "date": "2025-07-22T22:15",
    "location": "Providence",
    "priority": "Normal",
    "camOp": true,
    "shootType": "ENG",
    "notes": [],
    "camCount": 1,
    "onlyOneCamOp": true,
    "camAssignments": {
      "cam1": "",
      "cam2": "",
      "cam3": ""
    },
    "departureTime": "21:45",
    "filmingTime": "22:15",
    "assignedCamOps": [],
    "assignedDriver": "",
    "vehicle": "",
    "assignmentStatus": "Unassigned",
    "isReady": false,
    "status": "Pending",
    "assignedReporter": "Journalist: Emma Laporte",
    "vehicleStatus": "",
    "createdBy": "Admin",
    "createdAt": "2025-07-22T17:21:19.787Z",
    "id": "1753204879792",
    "deleted": true
  }
]